bottlenose/__init__.py
bottlenose/api.py
bottlenose/metadata.py
bottlenose-1.1.7.data/data/LICENSE
bottlenose-1.1.7.data/data/README.md
bottlenose-1.1.7.dist-info/DESCRIPTION.rst
bottlenose-1.1.7.dist-info/METADATA
bottlenose-1.1.7.dist-info/RECORD
bottlenose-1.1.7.dist-info/WHEEL
bottlenose-1.1.7.dist-info/metadata.json
bottlenose-1.1.7.dist-info/top_level.txt
